[  
   {  
      "text":"is OG slot open sir"},
   {  
      "text":"OG terms sir ?"},
   {  
      "text":"thanks for the info sir"},
   {  
      "text":"When to SubMMIT Wallet ?"},
   {  
      "text":"come on everyone cheer "},
   {  
      "text":"night night should push until OG"},
   {  
      "text":"coffee don't forget coffee"},
   {  
      "text":"ready my boss"},
   {  
      "text":"clowns all really haven't slept yet"},
   {  
      "text":"which person bang ?"},
   {  
      "text":"this work must be sultan"},
   {  
      "text":"greetings know bang "},
   {  
      "text":"for more works"},
   {  
      "text":"this is when ya distri?"},
   {  
      "text":"healthy continue comrades"},
   {  
      "text":"push until sleep"},
   {  
      "text":"When can JP"},
   {  
      "text":"LFG"},
   {  
      "text":"How can I participate in the airdrop?      "},
   {  
      "text":"How many tokens will be distributed during the airdrop?      "},
   {  
      "text":"What is the value of each token being airdropped?      "},
   {  
      "text":"Is there a minimum amount of Solana required to participate in the airdrop?      "},
   {  
      "text":"When will the airdrop take place?      "},
   {  
      "text":"How will I receive the airdropped tokens?      "},
   {  
      "text":"Is there a limit on the number of tokens that one person can receive during the airdrop?      "},
   {  
      "text":"What is the purpose of the airdrop?      "},
   {  
      "text":"What are the future plans for the airdropped token?      "},
   {  
      "text":"The spirit of the clown comrade "},
   {  
      "text":"Hello surya Fighter"},
   {  
      "text":"When is distri woy "},
   {  
      "text":"healthy continue comrades everyone "},
   {  
      "text":"how are you sister"},
   {  
      "text":"push until it hurts"},
   {  
      "text":"please give me OG sir"},
   {  
      "text":"you guys have been working on it for a long time "},
   {  
      "text":"to what level OG"},
   {  
      "text":"sleep guys "},
   {  
      "text":"which person is his dev"},
   {  
      "text":"morning noon night keep pushing"},
   {  
      "text":"it's been a long time to level up"},
   {  
      "text":"when can OG bair be able to sleep"},
   {  
      "text":"it's also fun if rame"},
   {  
      "text":"must be OG"},
   {  
      "text":"good job everyone "},
   {  
      "text":"Latest info "},
   {  
      "text":"read on the announcement"},
   {  
      "text":"see a lot of clowns"},
   {  
      "text":"relax comrade"},
   {  
      "text":"good sir."},
   {  
      "text":"Don't forget coffee comrades "},
   {  
      "text":"Don't Be Late to Eat Baby "},
   {  
      "text":"long time tired too "},
   {  
      "text":"Time is money "},
   {  
      "text":"surya fighter where the sound is"},
   {  
      "text":"tired, sleeping comrades"},
   {  
      "text":"you guys have been in this channel for a long time"},
   {  
      "text":"Latest News Check Announcements"},
   {  
      "text":"read correctly"},
   {  
      "text":"this airdrop is good ."},
   {  
      "text":"War of War "},
   {  
      "text":"guess when listing sir "},
   {  
      "text":"let'go OG"},
   {  
      "text":"what level is bang "},
   {  
      "text":"How to Quickly Level Up"},
   {  
      "text":"Latest Airdrop Link"},
   {  
      "text":"hello"},
   {  
      "text":"gm"},
   {  
      "text":"many indonesians "},
   {  
      "text":"Work Work "},
   {  
      "text":"tired too "},
   {  
      "text":"Working overtime like a horse"},
   {  
      "text":"spirit "},
   {  
      "text":"bang any new info ?"},
   {  
      "text":"rupiah fighters"},
   {  
      "text":"when og sir"}
]